pdevisualizer/__init__.py
pdevisualizer/boundary_conditions.py
pdevisualizer/enhanced_visualizations.py
pdevisualizer/heat2d.py
pdevisualizer/parameter_exploration.py
pdevisualizer/solver.py
pdevisualizer/wave2d.py
pdevisualizer-1.0.0.dist-info/licenses/LICENSE
pdevisualizer-1.0.0.dist-info/METADATA
pdevisualizer-1.0.0.dist-info/WHEEL
pdevisualizer-1.0.0.dist-info/top_level.txt
pdevisualizer-1.0.0.dist-info/RECORD
