Metadata-Version: 2.4
Name: pdevisualizer
Version: 1.0.0
Summary: A lightweight, high-performance Python library for prototyping and visualizing 2D/3D partial differential equations
Author-email: Aditya Anoop Nair <adityaanoop@live.in>
License-Expression: MIT
Project-URL: Homepage, https://github.com/AdityaAnoop3/pdevisualizer
Project-URL: Documentation, https://pdevisualizer.readthedocs.io
Project-URL: Repository, https://github.com/AdityaAnoop3/pdevisualizer
Project-URL: Bug Tracker, https://github.com/AdityaAnoop3/pdevisualizer/issues
Keywords: pde,partial-differential-equations,heat-equation,wave-equation,numerical-methods,finite-difference,scientific-computing,visualization,simulation,numba,matplotlib
Classifier: Development Status :: 4 - Beta
Classifier: Intended Audience :: Science/Research
Classifier: Intended Audience :: Education
Classifier: Programming Language :: Python :: 3
Classifier: Programming Language :: Python :: 3.10
Classifier: Programming Language :: Python :: 3.11
Classifier: Programming Language :: Python :: 3.12
Classifier: Topic :: Scientific/Engineering :: Physics
Classifier: Topic :: Scientific/Engineering :: Visualization
Classifier: Topic :: Scientific/Engineering :: Mathematics
Classifier: Operating System :: OS Independent
Requires-Python: >=3.10
License-File: LICENSE
Requires-Dist: numpy>=1.24.0
Requires-Dist: matplotlib>=3.7.0
Requires-Dist: numba>=0.57.0
Requires-Dist: scipy>=1.10.0
Provides-Extra: dev
Requires-Dist: pytest>=7.4.0; extra == "dev"
Requires-Dist: pytest-cov>=4.1.0; extra == "dev"
Requires-Dist: black>=23.0.0; extra == "dev"
Requires-Dist: flake8>=6.0.0; extra == "dev"
Requires-Dist: mypy>=1.5.0; extra == "dev"
Provides-Extra: docs
Requires-Dist: sphinx>=7.0.0; extra == "docs"
Requires-Dist: sphinx-rtd-theme>=1.3.0; extra == "docs"
Requires-Dist: sphinx-gallery>=0.14.0; extra == "docs"
Requires-Dist: numpydoc>=1.5.0; extra == "docs"
Requires-Dist: sphinx-autobuild>=2021.3.14; extra == "docs"
Dynamic: license-file
